bcubed_metrics/__init__.py
bcubed_metrics/bcubed.py
tests/__init__.py
tests/test_metrics.py
bcubed_metrics-1.0.1.dist-info/LICENSE.md
bcubed_metrics-1.0.1.dist-info/METADATA
bcubed_metrics-1.0.1.dist-info/WHEEL
bcubed_metrics-1.0.1.dist-info/top_level.txt
bcubed_metrics-1.0.1.dist-info/RECORD
