Metadata-Version: 2.1
Name: bcubed-metrics
Version: 1.0.1
Summary: A package to calculate BCUBED precision, recall, and F1-score for clustering evaluation.
Home-page: https://github.com/nezumiCodes/bcubed-metrics
Author: Vasiliki Nikolaidi
Project-URL: Homepage, https://github.com/nezumiCodes/bcubed-metrics
Keywords: bcubed
Classifier: Programming Language :: Python :: 3
Classifier: License :: OSI Approved :: MIT License
Classifier: Operating System :: OS Independent
Requires-Python: >=3.6
License-File: LICENSE.md
